LICENSE
README.md
setup.cfg
setup.py
bestsms/__init__.py
bestsms/_config.py
bestsms.egg-info/PKG-INFO
bestsms.egg-info/SOURCES.txt
bestsms.egg-info/dependency_links.txt
bestsms.egg-info/not-zip-safe
bestsms.egg-info/requires.txt
bestsms.egg-info/top_level.txt
bestsms/api/__init__.py
bestsms/api/actions/__init__.py
bestsms/api/actions/dtos/__init__.py
bestsms/api/actions/dtos/action_api_result_dto.py
bestsms/api/actions/requests/__init__.py
bestsms/api/actions/requests/_common.py
bestsms/api/actions/requests/abort.py
bestsms/api/actions/requests/reschedule.py
bestsms/api/actions/requests/resubmit.py
bestsms/api/actions/responses/__init__.py
bestsms/api/actions/responses/action_api_result.py
bestsms/api/addressbook/__init__.py
bestsms/api/addressbook/contactgroups/__init__.py
bestsms/api/addressbook/contactgroups/dtos/__init__.py
bestsms/api/addressbook/contactgroups/dtos/contact_group_api_create_request_dto.py
bestsms/api/addressbook/contactgroups/dtos/contact_group_api_result_dto.py
bestsms/api/addressbook/contactgroups/dtos/contact_group_list_api_result_dto.py
bestsms/api/addressbook/contactgroups/requests/__init__.py
bestsms/api/addressbook/contactgroups/requests/_common.py
bestsms/api/addressbook/contactgroups/requests/create.py
bestsms/api/addressbook/contactgroups/requests/delete.py
bestsms/api/addressbook/contactgroups/requests/detail.py
bestsms/api/addressbook/contactgroups/requests/list.py
bestsms/api/addressbook/contactgroups/responses/__init__.py
bestsms/api/addressbook/contactgroups/responses/contact_group_api_result.py
bestsms/api/addressbook/contactgroups/responses/contact_group_list_api_result.py
bestsms/api/addressbook/contacts/__init__.py
bestsms/api/addressbook/contacts/dtos/__init__.py
bestsms/api/addressbook/contacts/dtos/contact_api_result_dto.py
bestsms/api/addressbook/contacts/dtos/contact_list_api_result_dto.py
bestsms/api/addressbook/contacts/dtos/contact_model.py
bestsms/api/addressbook/contacts/requests/__init__.py
bestsms/api/addressbook/contacts/requests/_common.py
bestsms/api/addressbook/contacts/requests/create.py
bestsms/api/addressbook/contacts/requests/delete.py
bestsms/api/addressbook/contacts/requests/detail.py
