Metadata-Version: 2.1
Name: bestsms
Version: 2.4.0.2
Summary: BestSMS REST API Helper Library for Python
Home-page: https://bestsms.au
Author: BestSMS Australia
Author-email: info@bestsms.com.au
License: MIT
Keywords: bestsms,api,sms
Classifier: Development Status :: 5 - Production/Stable
Classifier: Intended Audience :: Developers
Classifier: License :: OSI Approved :: MIT License
Classifier: Programming Language :: Python
Classifier: Programming Language :: Python :: 3.9
Classifier: Programming Language :: Python :: 3.10
Classifier: Programming Language :: Python :: 3.11
Classifier: Programming Language :: Python :: 3.12
Classifier: Topic :: Software Development :: Libraries :: Python Modules
Classifier: Topic :: Communications :: Telephony
Classifier: Operating System :: OS Independent
License-File: LICENSE
Requires-Dist: requests
